{
    "name": "Your 1st Rocket",
    "icon": "beyond_earth:tier_1_rocket",
    "category": "beyond_earth:rocket_travel",
    "sortnum": 1,
    "pages": [
        {
            "type": "patchouli:text",
            "text": "Being your first rocket, you obviously have only resources you can find on Earth.$(br2)Using steel and iron, one can make a rocket barely powerful enough to leave orbit and make it to the closest celestial body, the Moon!"
        },
        {
            "type": "patchouli:entity",
            "entity": "beyond_earth:tier_1_rocket",
            "title": "Tier 1 Rocket",
            "offset": "0.5",
            "scale": "0.9"
        }
    ]
}