{
  "parent": "minecraft:recipes/root",
  "rewards": {
    "recipes": [
      "minecraft:cheese"
    ]
  },
  "criteria": {
    "has_cheese_block": {
      "trigger": "minecraft:inventory_changed",
      "conditions": {
        "items": [
          {
            "items": [
              "ad_astra:cheese_block"
            ]
          }
        ]
      }
    },
    "has_the_recipe": {
      "trigger": "minecraft:recipe_unlocked",
      "conditions": {
        "recipe": "minecraft:cheese"
      }
    }
  },
  "requirements": [
    [
      "has_cheese_block",
      "has_the_recipe"
    ]
  ]
}